mimosa/__init__.py
mimosa/cli.py
mimosa/dateswithoutdata.py
mimosa/dbt/dbt_project.yml
mimosa/dbt/models/country.sql
mimosa/dbt/models/country.yml
mimosa/dbt/models/gas_trace.sql
mimosa/dbt/models/overview.md
mimosa/dbt/models/sources.yml
mimosa/dbt/models/storage_lvl_facility.sql
mimosa/dbt/models/storage_lvl_facility.yml
mimosa/dbt/profiles.yml
mimosa/pipelines.py
mimosa/schemas/export/gas_storage.schema.yaml
mimosa/schemas/export/gas_storage_v2.schema.yaml
mimosa/schemas/import/gas_storage.schema.yaml
mimosa/schemas/import/gas_storage_v2.schema.yaml
mimosa/utilities.py
mimosa/wip.py
mimosa/wip_missing_dates.py
ternyxmimosa-0.9.0.dist-info/LICENSE.txt
ternyxmimosa-0.9.0.dist-info/METADATA
ternyxmimosa-0.9.0.dist-info/WHEEL
ternyxmimosa-0.9.0.dist-info/entry_points.txt
ternyxmimosa-0.9.0.dist-info/RECORD
