Metadata-Version: 2.1
Name: ternyxmimosa
Version: 0.9.0
Summary: A minimal modern data stack with working data pipelines in a single Docker container.
Home-page: https://github.com/EJOOSTEROP/mimosa
License: MIT
Keywords: x,y,z
Author: Erik Oosterop
Author-email: erik.oosterop.khesw@aleeas.com
Requires-Python: >=3.11
Classifier: License :: OSI Approved :: MIT License
Classifier: Programming Language :: Python :: 3
Classifier: Programming Language :: Python :: 3.11
Classifier: Programming Language :: Python :: 3.12
Requires-Dist: dlt[cli,filesystem,motherduck,parquet] (>=1.7.0,<2.0.0)
Requires-Dist: loguru (>=0.7.2,<0.8.0)
Requires-Dist: pandas (>=2.2.2,<3.0.0)
Requires-Dist: python-dotenv (>=1.0.0,<2.0.0)
Requires-Dist: sentry-sdk (>=2.20.6,<3.0.0)
Requires-Dist: streamlit (>=1.26.0,<2.0.0)
Project-URL: Documentation, https://github.com/EJOOSTEROP/mimosa
Project-URL: Repository, https://github.com/EJOOSTEROP/mimosa
